{
    "_links": {
        "self": {
            "href": "http:\/\/default\/sites\/default\/files\/embed_0.png"
        },
        "type": {
            "href": "http:\/\/drupal.org\/rest\/type\/file\/file"
        }
    },
    "fid": [
        {
            "value": 1
        }
    ],
    "uuid": [
        {
            "value": "6785cc78-a2e1-4bd1-ba50-30cacb8f7f78"
        }
    ],
    "langcode": [
        {
            "value": "en"
        }
    ],
    "filename": [
        {
            "value": "embed_0.png"
        }
    ],
    "uri": [
        {
            "value": "http:\/\/default\/sites\/default\/files\/embed_0.png"
        }
    ],
    "filemime": [
        {
            "value": "image\/png"
        }
    ],
    "filesize": [
        {
            "value": 728
        }
    ],
    "status": [
        {
            "value": true
        }
    ],
    "created": [
        {
            "value": 1494336334
        }
    ],
    "changed": [
        {
            "value": 1494336334
        }
    ]
}